README.rst
setup.py
django_infinite_memcached.egg-info/PKG-INFO
django_infinite_memcached.egg-info/SOURCES.txt
django_infinite_memcached.egg-info/dependency_links.txt
django_infinite_memcached.egg-info/top_level.txt
infinite_memcached/__init__.py
infinite_memcached/cache.py
infinite_memcached/models.py
infinite_memcached/tests.py