Metadata-Version: 1.1
Name: django-infinite-memcached
Version: 0.1
Summary: A Django memcached backend to handle 'infinite' timeouts
Home-page: http://github.com/edavis/django-infinite-memcached/
Author: Eric Davis
Author-email: ed@npri.org
License: BSD
Platform: UNKNOWN
Classifier: Framework :: Django
Classifier: Development Status :: 4 - Beta
Classifier: Intended Audience :: Developers
Classifier: License :: OSI Approved :: BSD License
